Wiz_Detention/__init__.py
Wiz_Detention/command.py
Wiz_Detention/constants.py
Wiz_Detention/game.py
Wiz_Detention/menu_screen.py
Wiz_Detention/open_window.py
Wiz_Detention/Assets/Maps/Acid_01.png
Wiz_Detention/Assets/Maps/Acid_TS.tsx
Wiz_Detention/Assets/Maps/Dungeon_Tiles_01.png
Wiz_Detention/Assets/Maps/Dungeon_Tiles_TS_1.tsx
Wiz_Detention/Assets/Maps/Level_0.tiled-project
Wiz_Detention/Assets/Maps/Level_0.tiled-session
Wiz_Detention/Assets/Maps/Level_0_map.json
Wiz_Detention/Assets/Maps/Level_0_map.tmx
Wiz_Detention/Assets/Maps/moveable_platforms.png
Wiz_Detention/Assets/Sprites/R_witch_stationary.png
Wiz_Detention/Assets/Sprites/cat05.png
Wiz_Detention-0.0.4.dist-info/LICENSE
Wiz_Detention-0.0.4.dist-info/METADATA
Wiz_Detention-0.0.4.dist-info/WHEEL
Wiz_Detention-0.0.4.dist-info/entry_points.txt
Wiz_Detention-0.0.4.dist-info/top_level.txt
Wiz_Detention-0.0.4.dist-info/RECORD
