Metadata-Version: 2.1
Name: Wiz-Detention
Version: 0.0.4
Summary: A python game
Author-email: Julia McKay <julia@ufl.edu>, Chandler Fox <chandler@ufl.edu>, Audrey DeHoog <adehoog@ufl.edu>
License: MIT License        
Project-URL: Github, https://github.com/juliamckay/WizDetention
Classifier: Programming Language :: Python :: 3
Classifier: License :: OSI Approved :: MIT License
Classifier: Operating System :: OS Independent
Requires-Python: >=3.10
License-File: LICENSE
Requires-Dist: arcade (>=2.6)
